{
  "P528489": {
    "name": "Simmi",
    "email": "",
    "phone": "",
    "password": "8588310a98676af6e22563c1559e1ae20f85950792bdcd0c8f334867c54581cd",
    "child": {
      "id": "C528489",
      "name": "Ria",
      "age": "11",
      "grade": "4th Grade"
    },
    "dysgraphiaResult": null,
    "registrationDate": "2025-09-13T16:02:09.064160",
    "lastActivity": "2025-09-13T16:02:30.595554"
  },
  "P422214": {
    "name": "Reena",
    "email": "",
    "phone": "",
    "password": "65e84be33532fb784c48129675f9eff3a682b27168c0ea744b2cf58ee02337c5",
    "child": {
      "id": "C422214",
      "name": "Jerry",
      "age": "12",
      "grade": "5th Grade"
    },
    "dysgraphiaResult": null,
    "registrationDate": "2025-09-13T16:17:02.786678",
    "lastActivity": "2025-09-13T16:17:02.786678"
  },
  "P508951": {
    "name": "Reena",
    "email": "",
    "phone": "",
    "password": "65e84be33532fb784c48129675f9eff3a682b27168c0ea744b2cf58ee02337c5",
    "child": {
      "id": "C508951",
      "name": "Jerry",
      "age": "12",
      "grade": "5th Grade"
    },
    "dysgraphiaResult": null,
    "registrationDate": "2025-09-13T16:18:29.264417",
    "lastActivity": "2025-09-13T16:18:48.092332"
  },
  "P597496": {
    "name": "Mira",
    "email": "",
    "phone": "",
    "password": "88b1cca59060320e5e5662a7da636884eb7580f4dc7e22cfb6f88b8f99045a71",
    "child": {
      "id": "C597496",
      "name": "Sara",
      "age": "13",
      "grade": "6th Grade"
    },
    "dysgraphiaResult": null,
    "registrationDate": "2025-09-13T16:19:58.076326",
    "lastActivity": "2025-09-13T16:23:48.239221"
  },
  "P267837": {
    "name": "Gina",
    "email": "",
    "phone": "",
    "password": "905e4948c4561a7698e0ed763e2bca1bc6d48ed18a8c6d8c6e3e7f3eca892207",
    "child": {
      "id": "C267837",
      "name": "Jess",
      "age": "11",
      "grade": "3rd Grade"
    },
    "dysgraphiaResult": null,
    "registrationDate": "2025-09-13T16:31:08.415207",
    "lastActivity": "2025-09-13T16:31:25.317590"
  },
  "P463203": {
    "name": "David",
    "email": "",
    "phone": "",
    "password": "88b1cca59060320e5e5662a7da636884eb7580f4dc7e22cfb6f88b8f99045a71",
    "child": {
      "id": "C463203",
      "name": "Rock",
      "age": "12",
      "grade": "4th Grade"
    },
    "dysgraphiaResult": null,
    "registrationDate": "2025-09-13T16:34:23.775900",
    "lastActivity": "2025-09-13T16:34:42.334953"
  },
  "P859271": {
    "name": "Jessica",
    "email": "",
    "phone": "",
    "password": "88b1cca59060320e5e5662a7da636884eb7580f4dc7e22cfb6f88b8f99045a71",
    "child": {
      "id": "C859271",
      "name": "Dave",
      "age": "",
      "grade": ""
    },
    "dysgraphiaResult": null,
    "registrationDate": "2025-09-13T16:40:59.844977",
    "lastActivity": "2025-09-13T16:41:12.762614"
  },
  "P093713": {
    "name": "David",
    "email": "",
    "phone": "",
    "password": "65e84be33532fb784c48129675f9eff3a682b27168c0ea744b2cf58ee02337c5",
    "child": {
      "id": "C093713",
      "name": "Jess",
      "age": "12",
      "grade": "5th Grade"
    },
    "dysgraphiaResult": null,
    "registrationDate": "2025-09-13T17:51:34.285187",
    "lastActivity": "2025-09-13T17:51:52.468087"
  },
  "P687889": {
    "name": "Mira",
    "email": "",
    "phone": "",
    "password": "88b1cca59060320e5e5662a7da636884eb7580f4dc7e22cfb6f88b8f99045a71",
    "child": {
      "id": "C687889",
      "name": "Simmi",
      "age": "",
      "grade": ""
    },
    "dysgraphiaResult": null,
    "registrationDate": "2025-09-13T18:01:28.465751",
    "lastActivity": "2025-09-13T18:05:25.334514"
  },
  "P502120": {
    "name": "Kajal",
    "email": "",
    "phone": "",
    "password": "8588310a98676af6e22563c1559e1ae20f85950792bdcd0c8f334867c54581cd",
    "child": {
      "id": "C502120",
      "name": "Mia",
      "age": "11",
      "grade": "2nd Grade"
    },
    "dysgraphiaResult": null,
    "registrationDate": "2025-09-14T10:38:22.700378",
    "lastActivity": "2025-09-14T10:38:35.583767"
  },
  "P582534": {
    "name": "Swati",
    "email": "",
    "phone": "",
    "password": "8588310a98676af6e22563c1559e1ae20f85950792bdcd0c8f334867c54581cd",
    "child": {
      "id": "C582534",
      "name": "Mihika",
      "age": "11",
      "grade": "3rd Grade"
    },
    "dysgraphiaResult": null,
    "registrationDate": "2025-09-14T11:29:42.845372",
    "lastActivity": "2025-10-04T08:48:57.077737"
  },
  "P776632": {
    "name": "Jaya",
    "email": "",
    "phone": "",
    "password": "88b1cca59060320e5e5662a7da636884eb7580f4dc7e22cfb6f88b8f99045a71",
    "child": {
      "id": "C776632",
      "name": "Kia",
      "age": "12",
      "grade": "4th Grade"
    },
    "dysgraphiaResult": null,
    "registrationDate": "2025-09-14T18:12:56.945654",
    "lastActivity": "2025-11-11T10:20:32.474642"
  },
  "P543236": {
    "name": "Kriti ",
    "email": "",
    "phone": "",
    "password": "88b1cca59060320e5e5662a7da636884eb7580f4dc7e22cfb6f88b8f99045a71",
    "child": {
      "id": "C543236",
      "name": "Dolly",
      "age": "11",
      "grade": "3rd Grade"
    },
    "dysgraphiaResult": null,
    "registrationDate": "2025-09-15T19:42:23.807924",
    "lastActivity": "2025-11-07T11:11:04.378076"
  }
}